bohr_atom/__init__.py
bohr_atom/bohr_atom.py
bohr_atom/constants.py
bohr_atom-0.1.1.dist-info/METADATA
bohr_atom-0.1.1.dist-info/WHEEL
bohr_atom-0.1.1.dist-info/top_level.txt
bohr_atom-0.1.1.dist-info/RECORD
