Metadata-Version: 2.4
Name: bohr-atom
Version: 0.1.1
Summary: Una librería para cálculos y visualizaciones del modelo atómico de Bohr
Author-email: Maria Moreno <maamorenor@udistrital.edu.co>, Juan <juan@example.com>
License: MIT
Project-URL: Homepage, https://github.com/Almarm-r/bohr_atom
Project-URL: Documentation, https://github.com/Almarm-r//bohr-atom#readme
Project-URL: Repository, https://github.com/Almarm-r//bohr-atom
Project-URL: Issues, https://github.com/Almarm-r//bohr-atom/issues
Keywords: physics,bohr,atom,quantum,hydrogen
Classifier: Development Status :: 3 - Alpha
Classifier: Intended Audience :: Education
Classifier: Intended Audience :: Science/Research
Classifier: License :: OSI Approved :: MIT License
Classifier: Programming Language :: Python :: 3
Classifier: Programming Language :: Python :: 3.8
Classifier: Programming Language :: Python :: 3.9
Classifier: Programming Language :: Python :: 3.10
Classifier: Programming Language :: Python :: 3.11
Classifier: Topic :: Scientific/Engineering :: Physics
Requires-Python: >=3.8
Requires-Dist: numpy>=1.20.0
Requires-Dist: matplotlib>=3.3.0
Provides-Extra: dev
Requires-Dist: pytest>=7.0.0; extra == "dev"
Requires-Dist: pytest-cov>=3.0.0; extra == "dev"
Requires-Dist: black>=22.0.0; extra == "dev"
Requires-Dist: flake8>=4.0.0; extra == "dev"
